api_gateway_ao/__init__.py
api_gateway_ao/version.py
api_gateway_ao/infrastructure/__init__.py
api_gateway_ao/infrastructure/ao.py
api_gateway_ao/infrastructure/do.py
api_gateway_ao-0.0.2.dist-info/LICENSE
api_gateway_ao-0.0.2.dist-info/METADATA
api_gateway_ao-0.0.2.dist-info/WHEEL
api_gateway_ao-0.0.2.dist-info/top_level.txt
api_gateway_ao-0.0.2.dist-info/RECORD
