Metadata-Version: 2.1
Name: api-gateway-ao
Version: 0.0.2
Summary: AO for api-gateway
Author: wangziling100
Author-email: wangziling100@163.com
Classifier: Programming Language :: Python :: 3
Classifier: License :: OSI Approved :: MIT License
License-File: LICENSE
